[
  {
    "version": "main",
    "title": "main",
    "aliases": []
  },
  {
    "version": "v0.26",
    "title": "v0.26",
    "aliases": [
      "latest"
    ]
  },
  {
    "version": "v0.25",
    "title": "v0.25",
    "aliases": []
  },
  {
    "version": "v0.24",
    "title": "v0.24",
    "aliases": []
  },
  {
    "version": "v0.23",
    "title": "v0.23",
    "aliases": []
  },
  {
    "version": "v0.22",
    "title": "v0.22",
    "aliases": []
  },
  {
    "version": "v0.21",
    "title": "v0.21",
    "aliases": []
  },
  {
    "version": "v0.20",
    "title": "v0.20",
    "aliases": []
  }
]
